fishspot/__init__.py
fishspot/assign.py
fishspot/detect.py
fishspot/distribute.py
fishspot/filter.py
fishspot/psf.py
fishspot/visualize.py
fishspot-0.5.0.dist-info/LICENSE
fishspot-0.5.0.dist-info/METADATA
fishspot-0.5.0.dist-info/WHEEL
fishspot-0.5.0.dist-info/top_level.txt
fishspot-0.5.0.dist-info/RECORD
