Metadata-Version: 2.1
Name: fishspot
Version: 0.5.0
Summary: Tools for finding discrete bright spots in images
Home-page: https://github.com/GFleishman/fishspot
Author: Greg M. Fleishman
Author-email: greg.nli10me@gmail.com
License: MIT
License-File: LICENSE
Requires-Dist: numpy
Requires-Dist: scipy
Requires-Dist: scikit-image
Requires-Dist: ClusterWrap
Requires-Dist: zarr
Requires-Dist: dask
Requires-Dist: dask[array]
